clea_api-0.2.2.dist-info/licenses/LICENSE
doc_loader/__init__.py
pipeline/__init__.py
stats/__init__.py
utils/__init__.py
utils/utils.py
vectordb/__init__.py
clea_api-0.2.2.dist-info/METADATA
clea_api-0.2.2.dist-info/WHEEL
clea_api-0.2.2.dist-info/top_level.txt
clea_api-0.2.2.dist-info/RECORD
