Metadata-Version: 2.4
Name: clea-api
Version: 0.2.2
Summary: Cléa-API: A framework for document load and hybrid search engine combining vector and metadata-based search. CRUD operations are performed using FastAPI.
Author-email: William <pikachu0442@gmail.com>
License-Expression: MIT
Project-URL: Homepage, https://willisback.github.io/clea-api/
Project-URL: Repository, https://github.com/WillIsback/clea-api
Project-URL: Documentation, https://willisback.github.io/clea-api/
Keywords: vector search,FastAPI,pgvector,hybrid search,CRUD,document load
Classifier: Development Status :: 4 - Beta
Classifier: Intended Audience :: Developers
Classifier: Topic :: Software Development :: Libraries
Classifier: Programming Language :: Python :: 3
Classifier: Programming Language :: Python :: 3.11
Requires-Python: >=3.11
License-File: LICENSE
Requires-Dist: fastapi==0.115.12
Requires-Dist: uvicorn==0.34.2
Requires-Dist: sqlalchemy==2.0.40
Requires-Dist: pgvector==0.4.1
Requires-Dist: pydantic==2.11.3
Requires-Dist: pytest==8.3.5
Requires-Dist: scikit-learn==1.6.1
Requires-Dist: sentence-transformers==4.1.0
Requires-Dist: transformers==4.51.3
Requires-Dist: torch==2.7.0
Requires-Dist: python-dotenv==1.1.0
Requires-Dist: requests==2.32.3
Requires-Dist: typer==0.15.3
Requires-Dist: watchfiles==1.0.5
Requires-Dist: ruff>=0.11.7
Dynamic: license-file
